udp_filetransfer/__init__.py
udp_filetransfer/__main__.py
udp_filetransfer/receiver.py
udp_filetransfer/sender.py
udp_filetransfer-0.4.5.dist-info/LICENSE
udp_filetransfer-0.4.5.dist-info/WHEEL
udp_filetransfer-0.4.5.dist-info/METADATA
udp_filetransfer-0.4.5.dist-info/RECORD
