Metadata-Version: 2.1
Name: udp-filetransfer
Version: 0.4.5
Summary: Reliable filetransfer over UDP
Home-page: https://gitlab.com/Trickster-Animations/udp-filetransfer
License: MPL-2.0
Author: golyalpha
Author-email: golyalpha@gmail.com
Requires-Python: >=3.7,<4.0
Classifier: Development Status :: 2 - Pre-Alpha
Classifier: Environment :: Console
Classifier: License :: OSI Approved
Classifier: Natural Language :: English
Classifier: Programming Language :: Python :: 3
Classifier: Programming Language :: Python :: 3.7
Classifier: Topic :: Communications :: File Sharing
Classifier: Topic :: Internet
Classifier: Topic :: Software Development :: Libraries
Classifier: Topic :: System :: Archiving :: Backup
Project-URL: Repository, https://gitlab.com/Trickster-Animations/udp-filetransfer
